aiomq/__init__.py
aiomq/bootstrap.py
aiomq/exception.py
aiomq/core/__init__.py
aiomq/core/clock.py
aiomq/core/data_warehouse.py
aiomq/core/logger.py
aiomq/core/push_queue.py
aiomq/core/receive_queue.py
aiomq/core/system_signals.py
aiomq/core/websocket.py
aiomq/core/worker_queue.py
aiomq/model/__init__.py
aiomq/model/reflect.py
aiomq/shortcut/__init__.py
aiomq/utils/__init__.py
aiomq/utils/network.py
aiomq/utils/response.py
aiomq/utils/translation.py
aiomq-0.2.4.dist-info/METADATA
aiomq-0.2.4.dist-info/WHEEL
aiomq-0.2.4.dist-info/entry_points.txt
aiomq-0.2.4.dist-info/top_level.txt
aiomq-0.2.4.dist-info/RECORD
