Metadata-Version: 2.1
Name: aiomq
Version: 0.2.4
Summary: UNKNOWN
Home-page: https://github.com/sqxccdy/aiomq
Author: Mason Sun
Author-email: sqxccdy@icloud.com
License: LGPL License
Keywords: aiohttp,mq,client
Platform: UNKNOWN
Classifier: Development Status :: 1 - Planning
Classifier: Intended Audience :: Developers
Classifier: License :: OSI Approved :: GNU Library or Lesser General Public License (LGPL)
Classifier: Operating System :: OS Independent
Classifier: Natural Language :: Chinese (Simplified)
Classifier: Programming Language :: Python
Classifier: Programming Language :: Python :: 3.8
Classifier: Topic :: Software Development :: Libraries
Classifier: Topic :: Utilities
Requires-Dist: aiohttp
